setup.py
redis_cluster_backend/__init__.py
redis_cluster_backend/backend.py
redis_cluster_backend.egg-info/PKG-INFO
redis_cluster_backend.egg-info/SOURCES.txt
redis_cluster_backend.egg-info/dependency_links.txt
redis_cluster_backend.egg-info/requires.txt
redis_cluster_backend.egg-info/top_level.txt
redis_cluster_backend.egg-info/zip-safe