Metadata-Version: 1.1
Name: redis-cluster-backend
Version: 0.1
Summary: redis cluster backend for celery
Home-page: http://github.com/ryankung/celery-redis-cluster-backend
Author: Ryan Kung
Author-email: ryankung@ieee.org
License: MIT
Keywords: celery redis cluster backend
Platform: UNKNOWN
Classifier: Development Status :: 4 - Beta
Classifier: Environment :: Console
Classifier: Programming Language :: Python :: 2.7
Classifier: Programming Language :: Python :: 3.5
Classifier: Operating System :: OS Independent
Classifier: Topic :: Software Development
Classifier: Topic :: Software Development :: Libraries :: Python Modules
